[
  {
    "id": 1,
    "type": 1,
    "emailAddress": "n@b.c",
    "password": "xyz",
    "fullName": "Nikola Tesla",
    "ticketList": []
  },
  {
    "id": 2,
    "type": 2,
    "emailAddress": "t@b.c",
    "password": "xyz",
    "fullName": "Thomas Edison",
    "ticketList": []
  },
  {
    "id": 3,
    "type": 3,
    "emailAddress": "g@b.c",
    "password": "xyz",
    "fullName": "George Washington",
    "ticketList": []
  },
  {
    "id": 0,
    "type": 1,
    "emailAddress": "bob@bob.com",
    "password": "xyz",
    "fullName": "Bob Com",
    "ticketList": []
  },
  {
    "id": 5,
    "type": 1,
    "emailAddress": "jyczhangnl@gmail.com",
    "password": "xyz",
    "fullName": "xyz",
    "ticketList": []
  },
  {
    "id": 6,
    "type": 1,
    "emailAddress": "1031469@hr.nl",
    "password": "rggr89]",
    "fullName": "megan pieters",
    "ticketList": []
  },
  {
    "id": 7,
    "type": 1,
    "emailAddress": "bob@com.c",
    "password": "ABCDef12#",
    "fullName": "Bob",
    "ticketList": []
  },
  {
    "id": 4,
    "type": 1,
    "emailAddress": "Meganpieters3@gmail.com",
    "password": "Megan2003@",
    "fullName": "Megan pieters",
    "ticketList": [
      1
    ]
  },
  {
    "id": 8,
    "type": 1,
    "emailAddress": "meganpieters3@gmail.com",
    "password": "Megan2003@",
    "fullName": "meg",
    "ticketList": []
  }
]